README.md
requirements.txt
setup.py
curve_fit/__init__.py
curve_fit/continuous.py
curve_fit/discontinuous.py
curve_fit.egg-info/PKG-INFO
curve_fit.egg-info/SOURCES.txt
curve_fit.egg-info/dependency_links.txt
curve_fit.egg-info/requires.txt
curve_fit.egg-info/top_level.txt