Metadata-Version: 1.1
Name: curve-fit
Version: 0.0.5
Summary: Curve fit
Home-page: https://github.com/samuel1205/curve_fit.git
Author: SamuelChan
Author-email: samuelchan1205@gmail.com
License: UNKNOWN
Platform: UNKNOWN
Classifier: Programming Language :: Python :: 3
Classifier: License :: OSI Approved :: MIT License
Classifier: Operating System :: OS Independent
